pyindrav2h/__init__.py
pyindrav2h/cli.py
pyindrav2h/connection.py
pyindrav2h/exceptions.py
pyindrav2h/v2hclient.py
pyindrav2h/v2hdevice.py
pyindrav2h-0.0.8.dist-info/LICENSE
pyindrav2h-0.0.8.dist-info/METADATA
pyindrav2h-0.0.8.dist-info/WHEEL
pyindrav2h-0.0.8.dist-info/entry_points.txt
pyindrav2h-0.0.8.dist-info/top_level.txt
pyindrav2h-0.0.8.dist-info/RECORD
