Metadata-Version: 2.1
Name: pyindrav2h
Version: 0.0.8
Summary: API client and example CLI to interact with Indra V2H Chargers
Author-email: Paul Morris <paul@creatingwake.com>
License: MIT License
Project-URL: Homepage, https://github.com/creatingwake/pyindrav2h
Keywords: v2h,indra,v2g,v2x
Classifier: License :: OSI Approved :: MIT License
Classifier: Programming Language :: Python
Classifier: Programming Language :: Python :: 3
Requires-Python: >=3.9
License-File: LICENSE
Requires-Dist: httpx
Requires-Dist: bs4
Requires-Dist: lxml
